{"name":"date","identifier":"TGQ6B7XRL5","description":null,"slotTypeName":"AMAZON.Date","obfuscationSetting":null,"valueElicitationSetting":{"promptSpecification":{"allowInterrupt":true,"messageGroupsList":[{"message":{"imageResponseCard":null,"ssmlMessage":null,"customPayload":null,"plainTextMessage":{"value":"Enter check-in date"}},"variations":null}],"maxRetries":4,"messageSelectionStrategy":"Random"},"slotConstraint":"Required","defaultValueSpecification":null,"sampleUtterances":null,"waitAndContinueSpecification":null},"multipleValuesSetting":null}